stellagban/Client.py
stellagban/__init__.py
stellagban-0.2.11.dist-info/METADATA
stellagban-0.2.11.dist-info/WHEEL
stellagban-0.2.11.dist-info/top_level.txt
stellagban-0.2.11.dist-info/RECORD
